protify/base_models/amplify.py
protify/base_models/ankh.py
protify/base_models/esm2.py
protify/base_models/esm3.py
protify/base_models/esmc.py
protify/base_models/get_base_models.py
protify/base_models/glm.py
protify/base_models/protbert.py
protify/base_models/proteinvec.py
protify/base_models/prott5.py
protify/base_models/random.py
protify/base_models/utils.py
protify/data/data_collators.py
protify/data/data_mixin.py
protify/data/dataset_classes.py
protify/data/supported_datasets.py
protify/data/utils.py
protify/embedder.py
protify/github_banner.png
protify/gui.py
protify/logger.py
protify/main.py
protify/metrics.py
protify/model_components/attention.py
protify/model_components/mlp.py
protify/model_components/transformer.py
protify/probes/get_probe.py
protify/probes/hybrid_probe.py
protify/probes/lazy_predict.py
protify/probes/linear_probe.py
protify/probes/losses.py
protify/probes/lyra_probe.py
protify/probes/retrivalnet.py
protify/probes/scikit_classes.py
protify/probes/scikit_hypers.py
protify/probes/trainers.py
protify/probes/transformer_probe.py
protify/protify_logo.png
protify/synthyra_logo.png
protify/utils.py
protify/visualization/ci_plots.py
protify/visualization/clustering.py
protify/visualization/plot_result.py
protify/visualization/reduce_dim.py
protify/yamls/base.yaml
protify/yamls/benchmark.yaml
protify-0.0.5.dist-info/LICENSE.md
protify-0.0.5.dist-info/METADATA
protify-0.0.5.dist-info/WHEEL
protify-0.0.5.dist-info/RECORD
