Metadata-Version: 2.3
Name: Protify
Version: 0.0.5
Summary: Low code molecular property prediction
License: Protify License
Keywords: plm, protein, transformer
Author: Synthyra
Author-email: info@synthyra.com
Requires-Python: >=3.8,<4.0
Classifier: License :: Other/Proprietary License
Classifier: Programming Language :: Python :: 3
Classifier: Programming Language :: Python :: 3.8
Classifier: Programming Language :: Python :: 3.9
Classifier: Programming Language :: Python :: 3.10
Classifier: Programming Language :: Python :: 3.11
Classifier: Programming Language :: Python :: 3.12
Classifier: Programming Language :: Python :: 3.13
Requires-Dist: accelerate (>=1.1.0)
Requires-Dist: datasets
Requires-Dist: einops
Requires-Dist: lightgbm
Requires-Dist: networkx (>=3.4.2)
Requires-Dist: numpy (==1.26.1)
Requires-Dist: pyfiglet
Requires-Dist: scikit-learn
Requires-Dist: scipy
Requires-Dist: tensorflow
Requires-Dist: tf-keras
Requires-Dist: torch (>=2.5.1)
Requires-Dist: torchinfo
Requires-Dist: torchmetrics
Requires-Dist: torchvision
Requires-Dist: transformers (>=4.47)
Requires-Dist: xgboost
Project-URL: Repository, https://github.com/Synthyra/Protify
